Brainshop/__init__.py
Brainshop-0.0.5.dist-info/LICENCE
Brainshop-0.0.5.dist-info/METADATA
Brainshop-0.0.5.dist-info/WHEEL
Brainshop-0.0.5.dist-info/top_level.txt
Brainshop-0.0.5.dist-info/RECORD
