Metadata-Version: 2.1
Name: Brainshop
Version: 0.0.5
Summary: An easy to use API wrapper for Brainshop.ai
Home-page: UNKNOWN
Author: Rishikesh
License: UNKNOWN
Platform: UNKNOWN
Requires-Dist: requests
